pydocedit.py
pydocedit-0.0.7.dist-info/LICENSE
pydocedit-0.0.7.dist-info/METADATA
pydocedit-0.0.7.dist-info/WHEEL
pydocedit-0.0.7.dist-info/top_level.txt
pydocedit-0.0.7.dist-info/RECORD
