Metadata-Version: 2.1
Name: pydocedit
Version: 0.0.7
Summary: A package to take edit doc/docx/trf files.
Home-page: https://www.drateendrajha.com/projects/pydocedit
Author: Ateendra Jha
Author-email: ateendrajha@live.com
Keywords: video,images,video2images,image crop
Classifier: Programming Language :: Python :: 3
Classifier: License :: OSI Approved :: MIT License
Classifier: Operating System :: OS Independent
Requires-Python: >=3.6
License-File: LICENSE
Requires-Dist: regex
Requires-Dist: comtypes
Requires-Dist: pillow
Requires-Dist: python-docx
Requires-Dist: nltk
Requires-Dist: pywin32
Requires-Dist: glob2
